blockbridge/__init__.py
blockbridge/base.py
blockbridge/exceptions.py
blockbridge/facade.py
blockbridge/s3_compatible.py
blockbridge/utils.py
blockbridge/operations/__init__.py
blockbridge/operations/clone.py
blockbridge/operations/sync.py
blockbridge/providers/__init__.py
blockbridge/providers/aws.py
blockbridge/providers/azure.py
blockbridge/providers/cloudflare.py
blockbridge/providers/gcs.py
blockbridge/providers/http.py
blockbridge/providers/wasabi.py
blockbridge-1.0.5.dist-info/METADATA
blockbridge-1.0.5.dist-info/WHEEL
blockbridge-1.0.5.dist-info/top_level.txt
blockbridge-1.0.5.dist-info/RECORD
