Metadata-Version: 2.4
Name: blockbridge
Version: 1.0.5
Summary: A resilient, multi-cloud storage library for GCS, S3, Azure, R2, Wasabi, and more.
Home-page: https://github.com/acx1729/blockbridge
Author: Anil Gaddam
Author-email: anil@gadd.am
License: MIT
Classifier: Development Status :: 4 - Beta
Classifier: Intended Audience :: Developers
Classifier: Topic :: Software Development :: Libraries :: Python Modules
Classifier: Topic :: System :: Filesystems
Classifier: License :: OSI Approved :: MIT License
Classifier: Programming Language :: Python :: 3
Classifier: Programming Language :: Python :: 3.9
Classifier: Programming Language :: Python :: 3.10
Classifier: Programming Language :: Python :: 3.11
Classifier: Operating System :: OS Independent
Requires-Python: >=3.9
Requires-Dist: google-cloud-storage>=2.0.0
Requires-Dist: boto3>=1.20.0
Requires-Dist: azure-storage-blob>=12.8.0
Requires-Dist: azure-identity>=1.7.0
Requires-Dist: requests>=2.25.0
Dynamic: author
Dynamic: author-email
Dynamic: classifier
Dynamic: description
Dynamic: description-content-type
Dynamic: home-page
Dynamic: license
Dynamic: requires-dist
Dynamic: requires-python
Dynamic: summary
